{
  "nprogress": "nprogress/nprogress.*",
  "requirejs": [ "requirejs/require.js", "requirejs-text/text.js", "require-css/css.js", "domready/ready.js", "domready/ready.min.js" ],
  "css-builder": [ "require-css/css-builder.js", "require-css/normalize.js" ],
  "headroom": "headroom.js/dist/headroom.js",
  "classie": [ "desandro-classie/classie.js" ],
  "font-awesome/fonts": [ "font-awesome/fonts" ],
  "kolayout": [ "kolayout/dist" ],
  "knockout": [ "knockout/build/output", "knockout-mapping/dist", "knockout-projections/dist" ],
  "q": [ "q/q.js" ],
  "open-sans-fontface": [ "open-sans-fontface/fonts", "open-sans-fontface/open-sans.less" ],
  "openlayers": [ "openlayers/dist" ],
  "proj4": [ "proj4/dist/proj4.js" ],
  "jsonpath": [ "jsonpath/jsonpath.min.js" ],
  "jquery": [ "jquery/dist" ],
  "jquery-ui": [ "jquery-ui/ui", "jquery-ui/themes/base" ],
  "signalr": [ "signalr/jquery.signalR.min.js" ],
  "c3": [ "d3/d3.min.js", "c3/c3.min.js", "c3/c3.min.css" ],
  "bootstrap": [ "bootstrap/dist" ],
  "bootstrap-switch": [ "bootstrap-switch/dist/js", "bootstrap-switch/dist/css" ],
  "bootstrap-datetimepicker": [ "eonasdan-bootstrap-datetimepicker/build" ],
  "si-portal-framework": [ "si-portal-framework/dist" ],
  "jsts": [ "jsts/dist" ],
  "gsap": [ "gsap/src/minified" ],
  "filesize": [ "filesize/lib/filesize.js" ],
  "pako": [ "pako/dist" ],
  "toastr": [ "toastr/build" ],
  "nouislider": [ "nouislider/distribute" ],
  "components-font-awesome": [ "components-font-awesome" ],
  "spectrum-colorpicker": [ "spectrum-colorpicker/spectrum.js", "spectrum-colorpicker/spectrum.css" ],
  "monaco-editor": [ "monaco-editor/min" ],
  "moment": [ "moment/min" ],
  "mapbox-gl": [ "mapbox-gl/dist" ],
  "es6-promise": "es6-promise/dist",
  "cesium": [ "ol-cesium/dist/Cesium" ],
  "olcesium": [ "ol-cesium/dist/olcesium.js", "ol-cesium/dist/ol.css" ]

}